cli_chef/bundle.py
cli_chef-0.1.0.dist-info/METADATA
cli_chef-0.1.0.dist-info/WHEEL
cli_chef-0.1.0.dist-info/entry_points.txt
cli_chef-0.1.0.dist-info/RECORD
