Metadata-Version: 2.3
Name: cli-chef
Version: 0.1.0
Summary: A CLI tool to bundle code files.
Author: Alex Thillen
Author-email: alexthillen852@gmail.com
Requires-Python: >=3.10,<4.0
Classifier: Programming Language :: Python :: 3
Classifier: Programming Language :: Python :: 3.10
Classifier: Programming Language :: Python :: 3.11
Classifier: Programming Language :: Python :: 3.12
Classifier: Programming Language :: Python :: 3.13
Requires-Dist: click (>=8.1.8,<9.0.0)
